structured_qa/__init__.py
structured_qa/cli.py
structured_qa/config.py
structured_qa/model_loaders.py
structured_qa/preprocessing.py
structured_qa/workflow.py
structured_qa-1.0.4.dist-info/LICENSE
structured_qa-1.0.4.dist-info/METADATA
structured_qa-1.0.4.dist-info/WHEEL
structured_qa-1.0.4.dist-info/entry_points.txt
structured_qa-1.0.4.dist-info/top_level.txt
structured_qa-1.0.4.dist-info/RECORD
