Metadata-Version: 2.2
Name: structured-qa
Version: 1.0.4
License: Apache-2.0
Project-URL: Documentation, https://mozilla-ai.github.io/structured-qa/
Project-URL: Issues, https://github.com/mozilla-ai/structured-qa/issues
Project-URL: Source, https://github.com/mozilla-ai/structured-qa
Requires-Python: >=3.10
License-File: LICENSE
Requires-Dist: fire
Requires-Dist: huggingface-hub
Requires-Dist: llama-cpp-python
Requires-Dist: loguru
Requires-Dist: pydantic
Requires-Dist: pymupdf4llm
Requires-Dist: pyyaml
Requires-Dist: rapidfuzz
Requires-Dist: streamlit
Provides-Extra: docs
Requires-Dist: mkdocs; extra == "docs"
Requires-Dist: mkdocs-material; extra == "docs"
Requires-Dist: mkdocstrings-python; extra == "docs"
Provides-Extra: tests
Requires-Dist: pytest<9,>=8; extra == "tests"
Requires-Dist: pytest-sugar>=0.9.6; extra == "tests"
Requires-Dist: pytest-mock>=3.14.0; extra == "tests"
